redfish/__init__.py
redfish/discovery/__init__.py
redfish/discovery/discovery.py
redfish/messages/__init__.py
redfish/messages/messages.py
redfish/rest/__init__.py
redfish/rest/v1.py
redfish/ris/__init__.py
redfish/ris/config.py
redfish/ris/ris.py
redfish/ris/rmc.py
redfish/ris/rmc_helper.py
redfish/ris/sharedtypes.py
redfish-3.3.3.dist-info/licenses/AUTHORS.md
redfish-3.3.3.dist-info/licenses/LICENSE.md
redfish-3.3.3.dist-info/METADATA
redfish-3.3.3.dist-info/WHEEL
redfish-3.3.3.dist-info/top_level.txt
redfish-3.3.3.dist-info/RECORD
