Metadata-Version: 2.4
Name: redfish
Version: 3.3.3
Summary: Redfish Python Library
Home-page: https://github.com/DMTF/python-redfish-library
Author: DMTF, https://www.dmtf.org/standards/feedback
License: BSD 3-clause "New" or "Revised License"
Keywords: Redfish
Classifier: Development Status :: 5 - Production/Stable
Classifier: License :: OSI Approved :: BSD License
Classifier: Programming Language :: Python :: 3
Classifier: Topic :: Communications
License-File: LICENSE.md
License-File: AUTHORS.md
Requires-Dist: jsonpath_rw
Requires-Dist: jsonpointer
Requires-Dist: requests
Requires-Dist: requests_toolbelt
Requires-Dist: requests-unixsocket
Requires-Dist: jsonpatch<=1.24; python_version == "3.4"
Requires-Dist: jsonpatch; python_version >= "3.5"
Dynamic: author
Dynamic: classifier
Dynamic: description
Dynamic: description-content-type
Dynamic: home-page
Dynamic: keywords
Dynamic: license
Dynamic: license-file
Dynamic: provides-extra
Dynamic: requires-dist
Dynamic: summary
